bitcash/__init__.py
bitcash/_ripemd160.py
bitcash/base58.py
bitcash/cashaddress.py
bitcash/cashtoken.py
bitcash/cli.py
bitcash/crypto.py
bitcash/curve.py
bitcash/exceptions.py
bitcash/format.py
bitcash/keygen.py
bitcash/op.py
bitcash/transaction.py
bitcash/utils.py
bitcash/wallet.py
bitcash/network/__init__.py
bitcash/network/meta.py
bitcash/network/rates.py
bitcash/network/services.py
bitcash/network/transaction.py
bitcash/network/APIs/BitcoinDotComAPI.py
bitcash/network/APIs/ChaingraphAPI.py
bitcash/network/APIs/FulcrumProtocolAPI.py
bitcash/network/APIs/__init__.py
bitcash/network/http/__init__.py
bitcash-1.1.2.dist-info/licenses/AUTHORS.md
bitcash-1.1.2.dist-info/licenses/LICENSE.txt
tests/__init__.py
tests/samples.py
tests/test_base58.py
tests/test_cashaddress.py
tests/test_cashtoken.py
tests/test_curve.py
tests/test_format.py
tests/test_transaction.py
tests/test_utils.py
tests/test_wallet.py
tests/utils.py
tests/network/__init__.py
tests/network/test_meta.py
tests/network/test_rates.py
tests/network/test_services.py
bitcash-1.1.2.dist-info/METADATA
bitcash-1.1.2.dist-info/WHEEL
bitcash-1.1.2.dist-info/entry_points.txt
bitcash-1.1.2.dist-info/top_level.txt
bitcash-1.1.2.dist-info/RECORD
