Metadata-Version: 2.4
Name: BitCash
Version: 1.1.2
Summary: Bitcoin Cash made easier.
Home-page: https://github.com/pybitcash/bitcash
Download-URL: https://github.com/pybitcash/bitcash/tarball/1.1.2
Author: Teran McKinney
Author-email: sega01@go-beyond.org
Maintainer: Corentin Mercier
Maintainer-email: corentin@mercier.link
License: MIT
Keywords: bitcoincash,cryptocurrency,payments,tools,wallet
Classifier: Development Status :: 4 - Beta
Classifier: Intended Audience :: Developers
Classifier: Intended Audience :: End Users/Desktop
Classifier: License :: OSI Approved :: MIT License
Classifier: Natural Language :: English
Classifier: Operating System :: OS Independent
Classifier: Programming Language :: Python :: 3.9
Classifier: Programming Language :: Python :: 3.10
Classifier: Programming Language :: Python :: 3.11
Classifier: Programming Language :: Python :: Implementation :: CPython
Classifier: Programming Language :: Python :: Implementation :: PyPy
License-File: LICENSE.txt
License-File: AUTHORS.md
Requires-Dist: coincurve>=4.3.0
Requires-Dist: requests
Provides-Extra: cli
Requires-Dist: appdirs; extra == "cli"
Requires-Dist: click; extra == "cli"
Requires-Dist: privy; extra == "cli"
Requires-Dist: tinydb; extra == "cli"
Provides-Extra: cache
Requires-Dist: lmdb; extra == "cache"
Dynamic: author
Dynamic: author-email
Dynamic: classifier
Dynamic: description
Dynamic: description-content-type
Dynamic: download-url
Dynamic: home-page
Dynamic: keywords
Dynamic: license
Dynamic: license-file
Dynamic: maintainer
Dynamic: maintainer-email
Dynamic: provides-extra
Dynamic: requires-dist
Dynamic: summary
